mantellum/__init__.py
mantellum/date_and_time_utils.py
mantellum/decorators.py
mantellum/logging_utils.py
mantellum/metrics.py
mantellum-1.0.4.dist-info/LICENSE
mantellum-1.0.4.dist-info/METADATA
mantellum-1.0.4.dist-info/WHEEL
mantellum-1.0.4.dist-info/top_level.txt
mantellum-1.0.4.dist-info/RECORD
