Metadata-Version: 2.1
Name: mantellum
Version: 1.0.4
Summary: Some common utils that might be useful to many Python projects
Home-page: https://github.com/nicc777/mantellum
Author: Nico Coetzee
Author-email: nicc777@gmail.com
Project-URL: Bug Tracker, https://github.com/nicc777/mantellum/issues
Classifier: Programming Language :: Python :: 3
Classifier: License :: OSI Approved :: GNU General Public License v3 (GPLv3)
Classifier: Operating System :: OS Independent
Classifier: Intended Audience :: System Administrators
Classifier: Intended Audience :: Developers
Classifier: Development Status :: 4 - Beta
Classifier: Environment :: Other Environment
Classifier: Environment :: Plugins
Classifier: Topic :: System :: Software Distribution
Classifier: Topic :: Utilities
Classifier: Topic :: Software Development
Classifier: Topic :: Software Development :: Libraries
Requires-Python: >=3.6
License-File: LICENSE
